LICENSE
MANIFEST.in
README.md
VERSION
requirements.txt
setup.cfg
setup.py
dockerfile_sec/__init__.py
dockerfile_sec/__main__.py
dockerfile_sec.egg-info/PKG-INFO
dockerfile_sec.egg-info/SOURCES.txt
dockerfile_sec.egg-info/dependency_links.txt
dockerfile_sec.egg-info/entry_points.txt
dockerfile_sec.egg-info/requires.txt
dockerfile_sec.egg-info/top_level.txt
dockerfile_sec.egg-info/zip-safe
dockerfile_sec/rules/core.yaml
dockerfile_sec/rules/credentials.yaml